medkit/__init__.py
medkit/api.py
medkit/scenario.py
medkit/bases/__head__.py
medkit/bases/__init__.py
medkit/bases/base_dataset.py
medkit/bases/base_domain.py
medkit/bases/base_env.py
medkit/bases/base_initialiser.py
medkit/bases/base_model.py
medkit/bases/base_policy.py
medkit/bases/base_reward.py
medkit/data/__init__.py
medkit/domains/__head__.py
medkit/domains/__init__.py
medkit/domains/cf.py
medkit/domains/icu.py
medkit/domains/mimic.py
medkit/domains/ward.py
medkit/environments/CounterfactualRNN.py
medkit/environments/SequentialVAE.py
medkit/environments/StateSpace.py
medkit/environments/TForce.py
medkit/environments/__head__.py
medkit/environments/__init__.py
medkit/environments/saved_models/__init__.py
medkit/environments/saved_models/icu_2_CRN.pth
medkit/environments/saved_models/icu_2_SVAE.pth
medkit/environments/saved_models/icu_2_statespace.pth
medkit/environments/saved_models/icu_2_tforce.pth
medkit/environments/saved_models/icu_4_CRN.pth
medkit/environments/saved_models/icu_4_SVAE.pth
medkit/environments/saved_models/icu_4_statespace.pth
medkit/environments/saved_models/icu_4_tforce.pth
medkit/environments/saved_models/icu_8_CRN.pth
medkit/environments/saved_models/icu_8_SVAE.pth
medkit/environments/saved_models/icu_8_statespace.pth
medkit/environments/saved_models/icu_8_tforce.pth
medkit/environments/saved_models/ward_2_CRN.pth
medkit/environments/saved_models/ward_2_SVAE.pth
medkit/environments/saved_models/ward_2_statespace.pth
medkit/environments/saved_models/ward_2_tforce.pth
medkit/environments/saved_models/ward_4_CRN.pth
medkit/environments/saved_models/ward_4_SVAE.pth
medkit/environments/saved_models/ward_4_statespace.pth
medkit/environments/saved_models/ward_4_tforce.pth
medkit/environments/saved_models/ward_8_CRN.pth
medkit/environments/saved_models/ward_8_SVAE.pth
medkit/environments/saved_models/ward_8_statespace.pth
medkit/environments/saved_models/ward_8_tforce.pth
medkit/initialisers/VAE.py
medkit/initialisers/__head__.py
medkit_learn-0.1.0.dist-info/LICENSE
medkit_learn-0.1.0.dist-info/METADATA
medkit_learn-0.1.0.dist-info/WHEEL
medkit_learn-0.1.0.dist-info/top_level.txt
medkit_learn-0.1.0.dist-info/RECORD
