Metadata-Version: 2.1
Name: medkit-learn
Version: 0.1.0
Summary: Medical sequential decision making simulation tools.
Home-page: https://github.com/XanderJC/medkit-learn
Author: Alex J. Chan
Author-email: alexjameschan@gmail.com
License: UNKNOWN
Platform: UNKNOWN
Classifier: Programming Language :: Python :: 3
Classifier: License :: OSI Approved :: MIT License
Classifier: Operating System :: OS Independent
Requires-Python: >=3.6
License-File: LICENSE
Requires-Dist: torch (>=1.7.0)
Requires-Dist: tqdm (>=4.54.1)
Requires-Dist: numpy (>=1.19.1)
Requires-Dist: pandas (>=1.1.2)
Requires-Dist: opacus (>=0.13.0)
Requires-Dist: gym (>=0.17.2)
Requires-Dist: scikit-learn (>=0.24.0)
